dosivuav_proj/__init__.py
dosivuav_proj/camera_cal/calibration1.jpg
dosivuav_proj/camera_cal/calibration10.jpg
dosivuav_proj/camera_cal/calibration11.jpg
dosivuav_proj/camera_cal/calibration12.jpg
dosivuav_proj/camera_cal/calibration13.jpg
dosivuav_proj/camera_cal/calibration14.jpg
dosivuav_proj/camera_cal/calibration15.jpg
dosivuav_proj/camera_cal/calibration16.jpg
dosivuav_proj/camera_cal/calibration17.jpg
dosivuav_proj/camera_cal/calibration18.jpg
dosivuav_proj/camera_cal/calibration19.jpg
dosivuav_proj/camera_cal/calibration2.jpg
dosivuav_proj/camera_cal/calibration20.jpg
dosivuav_proj/camera_cal/calibration3.jpg
dosivuav_proj/camera_cal/calibration4.jpg
dosivuav_proj/camera_cal/calibration5.jpg
dosivuav_proj/camera_cal/calibration6.jpg
dosivuav_proj/camera_cal/calibration7.jpg
dosivuav_proj/camera_cal/calibration8.jpg
dosivuav_proj/camera_cal/calibration9.jpg
dosivuav_proj/main.py
dosivuav_proj/processing/__init__.py
dosivuav_proj/processing/calculations.py
dosivuav_proj/processing/calibration.py
dosivuav_proj/processing/line_finding.py
dosivuav_proj/processing/perspective.py
dosivuav_proj/processing/threshold.py
dosivuav_proj/processing/undistort.py
dosivuav_proj/test_images/challange00101.jpg
dosivuav_proj/test_images/challange00111.jpg
dosivuav_proj/test_images/challange00136.jpg
dosivuav_proj/test_images/solidWhiteCurve.jpg
dosivuav_proj/test_images/solidWhiteRight.jpg
dosivuav_proj/test_images/solidYellowCurve.jpg
dosivuav_proj/test_images/solidYellowCurve2.jpg
dosivuav_proj/test_images/solidYellowLeft.jpg
dosivuav_proj/test_images/straight_lines1.jpg
dosivuav_proj/test_images/straight_lines2.jpg
dosivuav_proj/test_images/test1.jpg
dosivuav_proj/test_images/test2.jpg
dosivuav_proj/test_images/test3.jpg
dosivuav_proj/test_images/test4.jpg
dosivuav_proj/test_images/test5.jpg
dosivuav_proj/test_images/test6.jpg
dosivuav_proj/test_images/whiteCarLaneSwitch.jpg
dosivuav_proj/test_videos/challenge01.mp4
dosivuav_proj/test_videos/challenge02.mp4
dosivuav_proj-0.1.0.dist-info/METADATA
dosivuav_proj-0.1.0.dist-info/WHEEL
dosivuav_proj-0.1.0.dist-info/licenses/LICENSE
dosivuav_proj-0.1.0.dist-info/RECORD
