Metadata-Version: 2.4
Name: dosivuav-proj
Version: 0.1.0
Summary: A Python project for road lane detection
License: LICENSE
License-File: LICENSE
Author: wompbreaker
Author-email: wompbreaker@gmail.com
Maintainer: chedadsp
Requires-Python: >=3.11
Classifier: License :: Other/Proprietary License
Classifier: Programming Language :: Python :: 3
Classifier: Programming Language :: Python :: 3.11
Classifier: Programming Language :: Python :: 3.12
Classifier: Programming Language :: Python :: 3.13
Classifier: Programming Language :: Python :: 3.14
Requires-Dist: matplotlib (>=3.10.6,<4.0.0)
Requires-Dist: moviepy (>=2.2.1,<3.0.0)
Requires-Dist: opencv-python (>=4.12.0.88,<5.0.0.0)
